{"classificador": "LinearSVC", "accuracy": 0.6, "explosion": {"recall": 0.46153846153846156, "f1-score": 0.5901639344262295, "precision": 0.8181818181818182, "support": 39}, "siren": {"recall": 0.75, "f1-score": 0.75, "precision": 0.75, "support": 16}, "weighted avg": {"recall": 0.6, "f1-score": 0.5971578916934108, "precision": 0.6656543456543456, "support": 105}, "gunshot": {"recall": 0.42857142857142855, "f1-score": 0.5, "precision": 0.6, "support": 21}, "macro avg": {"recall": 0.6169240242516105, "f1-score": 0.6081891317547056, "precision": 0.6574300699300699, "support": 105}, "casual": {"recall": 0.8275862068965517, "f1-score": 0.5925925925925927, "precision": 0.46153846153846156, "support": 29}}