{"casual": {"precision": 0.31868131868131866, "recall": 1.0, "f1-score": 0.4833333333333333, "support": 29}, "explosion": {"precision": 1.0, "recall": 0.10256410256410256, "f1-score": 0.18604651162790695, "support": 39}, "gunshot": {"precision": 0.0, "recall": 0.0, "f1-score": 0.0, "support": 21}, "siren": {"precision": 1.0, "recall": 0.625, "f1-score": 0.7692307692307693, "support": 16}, "accuracy": 0.4095238095238095, "macro avg": {"precision": 0.5796703296703296, "recall": 0.43189102564102566, "f1-score": 0.35965265354800235, "support": 105}, "weighted avg": {"precision": 0.6118262689691262, "recall": 0.4095238095238095, "f1-score": 0.31981117074140325, "support": 105}, "classificador": "QuadraticDiscriminantAnalysis", "mediaTempoClassificacaoCadaAudio": 0.009332484290713356, "desvioTempoClassificacaoCadaAudio": 0.006456559939898928}