{"casual": {"precision": 0.3137254901960784, "recall": 0.5517241379310345, "f1-score": 0.4, "support": 29}, "explosion": {"precision": 0.7894736842105263, "recall": 0.7692307692307693, "f1-score": 0.7792207792207793, "support": 39}, "gunshot": {"precision": 0.0, "recall": 0.0, "f1-score": 0.0, "support": 21}, "siren": {"precision": 0.6875, "recall": 0.6875, "f1-score": 0.6875, "support": 16}, "accuracy": 0.5428571428571428, "macro avg": {"precision": 0.4476747936016512, "recall": 0.502113726790451, "f1-score": 0.46668019480519485, "support": 105}, "weighted avg": {"precision": 0.4846429799990172, "recall": 0.5428571428571428, "f1-score": 0.5046629560915276, "support": 105}, "classificador": "LinearDiscriminantAnalysis"}